pec/__init__.py
pec/version.py
pec/datasets/__init__.py
pec/datasets/csv/__init__.py
pec/datasets/csv/a1.csv
pec/datasets/csv/a2.csv
pec/datasets/csv/a3.csv
pec/datasets/csv/s1.csv
pec/datasets/csv/s2.csv
pec/datasets/csv/s3.csv
pec/datasets/csv/s4.csv
pec/datasets/csv/unbalance.csv
pec/ensemble/__init__.py
pec/ensemble/ensemble.py
pec/ensemble/inertia.py
pec/ensemble/result.py
pec/run/__init__.py
pec/run/kmeans.py
pec/run/result.py
pec/run/run.py
pec-2.0.1.dist-info/LICENSE
pec-2.0.1.dist-info/METADATA
pec-2.0.1.dist-info/WHEEL
pec-2.0.1.dist-info/top_level.txt
pec-2.0.1.dist-info/zip-safe
pec-2.0.1.dist-info/RECORD
