Metadata-Version: 2.1
Name: pec
Version: 2.0.1
Summary: PEC - Progressive Ensemble Clustering
Home-page: https://aware-diag-sapienza.github.io/pec
Download-URL: https://github.com/aware-diag-sapienza/pec/archive/refs/tags/v2.0.1.tar.gz
Author: A.WA.RE Research Group - Sapienza Università di Roma
Author-email: blasilli@diag.uniroma1.it
License: GNU General Public License (GPL)
Platform: Linux
Platform: Mac OS-X
Platform: Solaris
Platform: Unix
Platform: Windows
License-File: LICENSE
Requires-Dist: numpy
Requires-Dist: pandas
Requires-Dist: scikit-learn
